README.md
coalescenceml/__init__.py
coalescenceml/artifact_store/__init__.py
coalescenceml/artifact_store/base_artifact_store.py
coalescenceml/artifact_store/exceptions.py
coalescenceml/artifact_store/local_artifact_store.py
coalescenceml/artifacts/__init__.py
coalescenceml/artifacts/base_artifact.py
coalescenceml/artifacts/constants.py
coalescenceml/artifacts/data_analysis_artifact.py
coalescenceml/artifacts/data_artifact.py
coalescenceml/artifacts/metrics_artifact.py
coalescenceml/artifacts/model_artifact.py
coalescenceml/artifacts/type_registry.py
coalescenceml/cli/__init__.py
coalescenceml/cli/cli.py
coalescenceml/cli/config.py
coalescenceml/cli/core.py
coalescenceml/cli/hidden.py
coalescenceml/cli/integration.py
coalescenceml/cli/stack.py
coalescenceml/cli/stack_components.py
coalescenceml/cli/utils.py
coalescenceml/cli/version.py
coalescenceml/config/__init__.py
coalescenceml/config/base_config.py
coalescenceml/config/config_keys.py
coalescenceml/config/global_config.py
coalescenceml/config/profile_config.py
coalescenceml/constants.py
coalescenceml/container_registry/__init__.py
coalescenceml/container_registry/base_container_registry.py
coalescenceml/directory.py
coalescenceml/enums.py
coalescenceml/environment.py
coalescenceml/exceptions.py
coalescenceml/experiment_tracker/__init__.py
coalescenceml/experiment_tracker/base_experiment_tracker.py
coalescenceml/integrations/__init__.py
coalescenceml/integrations/aws_s3/__init__.py
coalescenceml/integrations/aws_s3/artifact_store/__init__.py
coalescenceml/integrations/aws_s3/artifact_store/aws_artifact_store.py
coalescenceml/integrations/azure_datalake/__init__.py
coalescenceml/integrations/azure_datalake/artifact_store/__init__.py
coalescenceml/integrations/azure_datalake/artifact_store/azure_artifact_store.py
coalescenceml/integrations/constants.py
coalescenceml/integrations/exceptions.py
coalescenceml/integrations/integration.py
coalescenceml/integrations/mlflow/__init__.py
coalescenceml-0.5.1.dist-info/entry_points.txt
coalescenceml-0.5.1.dist-info/LICENSE
coalescenceml-0.5.1.dist-info/WHEEL
coalescenceml-0.5.1.dist-info/METADATA
coalescenceml-0.5.1.dist-info/RECORD
